[
  {
    "rank": 1,
    "score": 25,
    "rating": 1907,
    "username": "vonWerlich",
    "performance": 1875
  },
  {
    "rank": 2,
    "score": 20,
    "rating": 1946,
    "username": "OReal",
    "performance": 1982
  },
  {
    "rank": 3,
    "score": 20,
    "rating": 2051,
    "username": "kronossaurus",
    "performance": 1928
  },
  {
    "rank": 4,
    "score": 16,
    "rating": 1745,
    "username": "Modestovic",
    "performance": 1685
  },
  {
    "rank": 5,
    "score": 15,
    "rating": 1814,
    "username": "KP-NexT",
    "flair": "symbols.fleur-de-lis",
    "performance": 1800
  },
  {
    "rank": 6,
    "score": 14,
    "rating": 1774,
    "username": "L_L1999",
    "performance": 1597
  },
  {
    "rank": 7,
    "score": 14,
    "rating": 1661,
    "username": "DuuNexT",
    "performance": 1552
  },
  {
    "rank": 8,
    "score": 12,
    "rating": 1652,
    "username": "Maycon_Schlickmann",
    "performance": 1682
  },
  {
    "rank": 9,
    "score": 12,
    "rating": 1443,
    "username": "rlemos",
    "performance": 1536
  },
  {
    "rank": 10,
    "score": 11,
    "rating": 1660,
    "username": "GSibowicz",
    "performance": 1650
  },
  {
    "rank": 11,
    "score": 11,
    "rating": 1315,
    "username": "jaop",
    "performance": 1382
  },
  {
    "rank": 12,
    "score": 10,
    "rating": 1559,
    "username": "LPSupi_sac",
    "performance": 1727
  },
  {
    "rank": 13,
    "score": 10,
    "rating": 1570,
    "username": "BSid3_DCLXVI",
    "performance": 1562
  },
  {
    "rank": 14,
    "score": 10,
    "rating": 1664,
    "username": "RogerRScar",
    "performance": 1508
  },
  {
    "rank": 15,
    "score": 10,
    "rating": 1606,
    "username": "VanildoSDanielski",
    "performance": 1386
  },
  {
    "rank": 16,
    "score": 10,
    "rating": 1134,
    "username": "Syfere",
    "performance": 1376
  },
  {
    "rank": 17,
    "score": 9,
    "rating": 1512,
    "username": "Claudio1414",
    "performance": 1471
  },
  {
    "rank": 18,
    "score": 9,
    "rating": 1323,
    "username": "lucksoitenta",
    "performance": 1385
  },
  {
    "rank": 19,
    "score": 8,
    "rating": 1344,
    "username": "Matheus447",
    "performance": 1336
  },
  {
    "rank": 20,
    "score": 6,
    "rating": 999,
    "username": "DantonJosh",
    "flair": "symbols.rainbow-flag",
    "performance": 1185
  },
  {
    "rank": 21,
    "score": 6,
    "rating": 1006,
    "username": "ncc_bee",
    "performance": 1096
  },
  {
    "rank": 22,
    "score": 4,
    "rating": 1932,
    "username": "Slinky95",
    "performance": 2044
  },
  {
    "rank": 23,
    "score": 4,
    "rating": 1344,
    "username": "proneer",
    "performance": 1624
  },
  {
    "rank": 24,
    "score": 2,
    "rating": 1496,
    "username": "Diiieferson",
    "performance": 1364
  },
  {
    "rank": 25,
    "score": 2,
    "rating": 1306,
    "username": "feliperuivofuga",
    "performance": 1345
  },
  {
    "rank": 26,
    "score": 2,
    "rating": 1152,
    "username": "PedroNEXT",
    "performance": 1122
  },
  {
    "rank": 27,
    "score": 2,
    "rating": 1028,
    "username": "antoniogoulart",
    "performance": 970
  },
  {
    "rank": 28,
    "score": 0,
    "rating": 1212,
    "username": "hermesthatgoout",
    "performance": 0
  },
  {
    "rank": 29,
    "score": 0,
    "rating": 1093,
    "username": "axt2106",
    "performance": 1065
  },
  {
    "rank": 30,
    "score": 0,
    "rating": 1047,
    "username": "gusCamargo",
    "performance": 0
  },
  {
    "rank": 31,
    "score": 0,
    "rating": 954,
    "username": "Gustavo972",
    "performance": 957
  }
]