[{"rank": 1, "score": 59, "rating": 2186, "username": "vonWerlich", "performance": 1957}, {"rank": 2, "score": 27, "rating": 1882, "username": "gadottL", "performance": 1766}, {"rank": 3, "score": 24, "rating": 1342, "username": "samuelperuw", "performance": 1535}, {"rank": 4, "score": 23, "rating": 1674, "username": "sonogrinhas", "performance": 1636}, {"rank": 5, "score": 22, "rating": 1686, "username": "Modestovic", "performance": 1690}, {"rank": 6, "score": 22, "rating": 1595, "username": "NegroMestrovisk", "performance": 1575}, {"rank": 7, "score": 21, "rating": 1817, "username": "AndreHLLMAB251", "performance": 1853}, {"rank": 8, "score": 21, "rating": 1476, "username": "ReneDeVilla", "performance": 1499}, {"rank": 9, "score": 20, "rating": 1477, "username": "Soresu1", "performance": 1570}, {"rank": 10, "score": 20, "rating": 1043, "username": "adrizinhadochess", "performance": 1389}, {"rank": 11, "score": 19, "rating": 1801, "username": "AlexanderMAVC", "performance": 1931}, {"rank": 12, "score": 19, "rating": 1582, "username": "edilbertocordeirojr", "performance": 1688}, {"rank": 13, "score": 19, "rating": 1546, "username": "JonArt_25", "performance": 1527}, {"rank": 14, "score": 17, "rating": 1929, "username": "FabioSLMA261A", "performance": 1684}, {"rank": 15, "score": 17, "rating": 1515, "username": "DantonJosh", "flair": "symbols.rainbow-flag", "performance": 1470}, {"rank": 16, "score": 16, "rating": 1347, "username": "paodequeijochess", "flair": "objects.teddy-bear", "performance": 1426}, {"rank": 17, "score": 12, "rating": 1399, "username": "Yukizz", "performance": 1566}, {"rank": 18, "score": 12, "rating": 1466, "username": "Biipityboopity", "flair": "nature.sun", "performance": 1478}, {"rank": 19, "score": 11, "rating": 1369, "username": "VitorKMLMA261B", "performance": 1406}, {"rank": 20, "score": 11, "rating": 1566, "username": "PauloMSJLMA261A", "performance": 1404}, {"rank": 21, "score": 11, "rating": 1168, "username": "CaioVADaSLMA261B", "performance": 1230}, {"rank": 22, "score": 10, "rating": 1665, "username": "LFNishi", "performance": 1819}, {"rank": 23, "score": 10, "rating": 1646, "username": "carlosfisica", "performance": 1635}, {"rank": 24, "score": 10, "rating": 1438, "username": "MatheusSKLMA261A", "flair": "smileys.distorted-face", "performance": 1584}, {"rank": 25, "score": 10, "rating": 1484, "username": "santcar7", "flair": "smileys.cold-face", "performance": 1458}, {"rank": 26, "score": 8, "rating": 1328, "username": "MiguelPSLMA261A", "performance": 1516}, {"rank": 27, "score": 8, "rating": 1473, "username": "LuisHGSBLMA261B", "performance": 1497}, {"rank": 28, "score": 8, "rating": 1309, "username": "AdrissonKLMA262B", "performance": 1311}, {"rank": 29, "score": 8, "rating": 1267, "username": "EmanuelESBLMA261B", "performance": 1262}, {"rank": 30, "score": 7, "rating": 1495, "username": "RianLLLMA261B", "performance": 1400}, {"rank": 31, "score": 7, "rating": 1039, "username": "LeviOMLMA261A", "performance": 1272}, {"rank": 32, "score": 7, "rating": 1236, "username": "GuilhermePMLMA261A", "performance": 1180}, {"rank": 33, "score": 7, "rating": 1490, "username": "LeticiaSLMA261A", "performance": 1161}, {"rank": 34, "score": 7, "rating": 1252, "username": "BrenoGGLMA261B", "performance": 1129}, {"rank": 35, "score": 7, "rating": 1031, "username": "VitorHLVLMA261A", "performance": 1109}, {"rank": 36, "score": 6, "rating": 1195, "username": "HelenaDaSCLMA261B", "flair": "smileys.alien-monster", "performance": 1254}, {"rank": 37, "score": 6, "rating": 1161, "username": "GustavoMALMA261A", "performance": 1253}, {"rank": 38, "score": 6, "rating": 1129, "username": "LuisDFCLMA261A", "performance": 1236}, {"rank": 39, "score": 6, "rating": 1221, "username": "MiguelRCLMA261B", "performance": 1132}, {"rank": 40, "score": 6, "rating": 1173, "username": "DAVIFCLMA261A", "performance": 1123}, {"rank": 41, "score": 6, "rating": 1179, "username": "LeticiaSMFLMA261B", "performance": 1122}, {"rank": 42, "score": 6, "rating": 1272, "username": "SophiaMFFLMA261A", "performance": 1082}, {"rank": 43, "score": 6, "rating": 1201, "username": "LeviNRLMA261A", "performance": 1017}, {"rank": 44, "score": 5, "rating": 1422, "username": "JoaoPRdaSLMA261A", "performance": 1427}, {"rank": 45, "score": 5, "rating": 1382, "username": "LucasETMLMA261A", "performance": 1301}, {"rank": 46, "score": 5, "rating": 1158, "username": "IsabelliLRLMA261B", "performance": 1270}, {"rank": 47, "score": 5, "rating": 1171, "username": "PedroAIELMA261B", "performance": 1183}, {"rank": 48, "score": 5, "rating": 1056, "username": "KatleenMSLMA261A", "performance": 1042}, {"rank": 49, "score": 5, "rating": 1096, "username": "EduardaRSLMA261A", "flair": "smileys.ghost", "performance": 1013}, {"rank": 50, "score": 5, "rating": 959, "username": "MiguelFALMA261A", "performance": 944}, {"rank": 51, "score": 4, "rating": 1617, "username": "sorrygmsorry", "performance": 1640}, {"rank": 52, "score": 4, "rating": 1301, "username": "MATEUSSdaSLMAA251", "flair": "smileys.thinking-face", "performance": 1246}, {"rank": 53, "score": 4, "rating": 1157, "username": "JuliaITRLMA261B", "performance": 1170}, {"rank": 54, "score": 4, "rating": 1248, "username": "GuilhermeKPLMA261B", "performance": 1059}, {"rank": 55, "score": 4, "rating": 1092, "username": "CarlosCCMLMA261B", "performance": 989}, {"rank": 56, "score": 4, "rating": 1054, "username": "KenzoJSGLMA261A", "performance": 969}, {"rank": 57, "score": 3, "rating": 1084, "username": "JoaoAFLMA261B", "performance": 1089}, {"rank": 58, "score": 3, "rating": 999, "username": "JoaoVPRLMA261B", "flair": "smileys.cold-face", "performance": 1060}, {"rank": 59, "score": 3, "rating": 959, "username": "JuliaPGLMA261B", "performance": 993}, {"rank": 60, "score": 3, "rating": 829, "username": "GuilhermeCLMA261A", "performance": 924}, {"rank": 61, "score": 3, "rating": 884, "username": "CamilaDCLMA261B", "flair": "smileys.skull", "performance": 868}, {"rank": 62, "score": 2, "rating": 1394, "username": "MatheusRJLMAA251", "performance": 1429}, {"rank": 63, "score": 2, "rating": 960, "username": "PedroHdaSMLMA261B", "performance": 891}, {"rank": 64, "score": 1, "rating": 2013, "username": "MarcusZulu", "performance": 1708}, {"rank": 65, "score": 0, "rating": 1205, "username": "KaioLALMA261B"}, {"rank": 66, "score": 0, "rating": 691, "username": "SamuelPLMA261B", "performance": 1010}, {"rank": 67, "score": 0, "rating": 883, "username": "GabrielGCLMA261A", "performance": 603}]