[
  {
    "rank": 1,
    "score": 36,
    "rating": 2269,
    "username": "Re2_Re7",
    "performance": 1890
  },
  {
    "rank": 2,
    "score": 22,
    "rating": 1702,
    "username": "Modestovic",
    "performance": 1825
  },
  {
    "rank": 3,
    "score": 20,
    "rating": 1917,
    "username": "vonWerlich",
    "performance": 1933
  },
  {
    "rank": 4,
    "score": 18,
    "rating": 1495,
    "username": "rlemos",
    "performance": 1538
  },
  {
    "rank": 5,
    "score": 18,
    "rating": 1624,
    "username": "Velho_moinho",
    "performance": 1497
  },
  {
    "rank": 6,
    "score": 15,
    "rating": 1498,
    "username": "Claudio1414",
    "performance": 1415
  },
  {
    "rank": 7,
    "score": 14,
    "rating": 1531,
    "username": "Diiieferson",
    "performance": 1537
  },
  {
    "rank": 8,
    "score": 13,
    "rating": 1596,
    "username": "Bohr274",
    "performance": 1525
  },
  {
    "rank": 9,
    "score": 12,
    "rating": 1455,
    "username": "DuuNexT",
    "performance": 1569
  },
  {
    "rank": 10,
    "score": 11,
    "rating": 1517,
    "username": "ShaolimMataPorco",
    "performance": 1528
  },
  {
    "rank": 11,
    "score": 11,
    "rating": 1138,
    "username": "PedroNEXT",
    "performance": 1354
  },
  {
    "rank": 12,
    "score": 10,
    "rating": 1015,
    "username": "Gustavo972",
    "performance": 1307
  },
  {
    "rank": 13,
    "score": 8,
    "rating": 1479,
    "username": "DanielChamposki",
    "performance": 1470
  },
  {
    "rank": 14,
    "score": 8,
    "rating": 1289,
    "username": "IzaacSI",
    "performance": 1337
  },
  {
    "rank": 15,
    "score": 8,
    "rating": 1057,
    "username": "DantonJosh",
    "flair": "symbols.rainbow-flag",
    "performance": 1237
  },
  {
    "rank": 16,
    "score": 6,
    "rating": 1663,
    "username": "Maycon_Schlickmann",
    "performance": 2169
  },
  {
    "rank": 17,
    "score": 6,
    "rating": 1296,
    "username": "jaop",
    "performance": 1251
  },
  {
    "rank": 18,
    "score": 5,
    "rating": 962,
    "username": "ncc_bee",
    "performance": 999
  },
  {
    "rank": 19,
    "score": 4,
    "rating": 1100,
    "username": "Vinove",
    "performance": 1091
  },
  {
    "rank": 20,
    "score": 3,
    "rating": 1041,
    "username": "gusCamargo",
    "performance": 1186
  },
  {
    "rank": 21,
    "score": 2,
    "rating": 1116,
    "username": "hermesthatgoout",
    "performance": 1048
  },
  {
    "rank": 22,
    "score": 2,
    "rating": 1053,
    "username": "axt2106",
    "performance": 918
  }
]