{
  "nbPlayers": 14,
  "duels": [],
  "isFinished": true,
  "podium": [
    {
      "name": "vonWerlich",
      "rank": 1,
      "rating": 2104,
      "score": 20,
      "nb": {
        "game": 13,
        "berserk": 0,
        "win": 10
      },
      "performance": 1806
    },
    {
      "name": "jaop",
      "rank": 2,
      "rating": 1354,
      "score": 10,
      "nb": {
        "game": 9,
        "berserk": 0,
        "win": 5
      },
      "performance": 1521
    },
    {
      "name": "DantonJosh",
      "flair": "symbols.rainbow-flag",
      "rank": 3,
      "rating": 1205,
      "score": 9,
      "nb": {
        "game": 11,
        "berserk": 0,
        "win": 4
      },
      "performance": 1554
    }
  ],
  "pairingsClosed": true,
  "stats": {
    "games": 37,
    "moves": 1844,
    "whiteWins": 17,
    "blackWins": 19,
    "draws": 1,
    "berserks": 0,
    "averageRating": 1556
  },
  "standing": {
    "page": 1,
    "players": [
      {
        "name": "vonWerlich",
        "rank": 1,
        "rating": 2104,
        "score": 20,
        "sheet": {
          "scores": "2220222202220"
        }
      },
      {
        "name": "jaop",
        "rank": 2,
        "rating": 1354,
        "score": 10,
        "sheet": {
          "scores": "022022200"
        }
      },
      {
        "name": "DantonJosh",
        "flair": "symbols.rainbow-flag",
        "rank": 3,
        "rating": 1205,
        "score": 9,
        "sheet": {
          "scores": "02020201002"
        }
      },
      {
        "name": "the-chemist",
        "rank": 4,
        "rating": 2177,
        "score": 8,
        "sheet": {
          "scores": "2222"
        }
      },
      {
        "name": "SK_math",
        "rank": 5,
        "rating": 2232,
        "score": 8,
        "sheet": {
          "scores": "2222"
        }
      },
      {
        "name": "Modestovic",
        "rank": 6,
        "rating": 1821,
        "score": 6,
        "sheet": {
          "scores": "0022020"
        }
      },
      {
        "name": "DuuDragao_Next",
        "rank": 7,
        "rating": 1482,
        "score": 5,
        "sheet": {
          "scores": "002001020"
        }
      },
      {
        "name": "Gustavo972",
        "rank": 8,
        "rating": 1460,
        "score": 4,
        "sheet": {
          "scores": "0022"
        }
      },
      {
        "name": "Matheus447",
        "rank": 9,
        "rating": 1373,
        "score": 2,
        "sheet": {
          "scores": "20"
        }
      },
      {
        "name": "RafaBabu",
        "rank": 10,
        "rating": 1355,
        "score": 2,
        "sheet": {
          "scores": "002"
        }
      }
    ]
  },
  "id": "UywgbMbR",
  "createdBy": "the-chemist",
  "startsAt": "2021-10-22T21:30:00Z",
  "system": "arena",
  "fullName": "Sextas Xadrez Online - T04 Arena",
  "minutes": 120,
  "perf": {
    "key": "blitz",
    "name": "Blitz",
    "icon": ")"
  },
  "clock": {
    "limit": 300,
    "increment": 3
  },
  "variant": "standard",
  "rated": true,
  "noStreak": true,
  "verdicts": {
    "list": [
      {
        "condition": "Must be in team NexT - Núcleo de Estudos em Xadrez & Tecnologias",
        "verdict": "ok"
      }
    ],
    "accepted": true
  },
  "description": "Torneio de Treinamento da ação \"Sextas Xadrez Online\" do projeto \"Comunidade de Prática Online\" do NexT, sem limite de rating, aberto a todos que se juntarem à equipe do NexT no Lichess (Clube Virtual Online do NexT).",
  "teamMember": "next-nucleo-de-estudos-em-xadrez--tecnologias"
}